streamerate/__init__.py
streamerate/__init__.pyi
streamerate/streams.py
streamerate/tests/__init__.py
streamerate/tests/test_buffered_stream.py
streamerate/tests/test_import.py
streamerate/tests/test_Streams.py
streamerate-1.2.4.dist-info/entry_points.txt
streamerate-1.2.4.dist-info/licenses/LICENSE
streamerate-1.2.4.dist-info/METADATA
streamerate-1.2.4.dist-info/WHEEL
streamerate-1.2.4.dist-info/RECORD
