Metadata-Version: 2.4
Name: streamerate
Version: 1.2.4
Summary: streamerate: a fluent and expressive Python library for chainable iterable processing, inspired by Java 8 streams.
License: MIT
License-File: LICENSE
Author: Andrei Suiu
Author-email: andrei.suiu@gmail.com
Requires-Python: >=3.10,<4.0.0
Classifier: License :: OSI Approved :: MIT License
Classifier: Programming Language :: Python :: 3
Classifier: Programming Language :: Python :: 3.10
Classifier: Programming Language :: Python :: 3.11
Classifier: Programming Language :: Python :: 3.12
Classifier: Programming Language :: Python :: 3.13
Classifier: Programming Language :: Python :: 3.14
Provides-Extra: gevent
Requires-Dist: gevent (>=24.2.1) ; (python_version >= "3.10" and python_version < "3.14") and (extra == "gevent")
Requires-Dist: tblib (>=1.7.0)
Requires-Dist: throttlex (>=1.0.0)
Requires-Dist: tqdm (>=4.62.0)
Project-URL: Repository, https://github.com/asuiu/streamerate
